CHANGES.rst
MANIFEST.in
README.rst
requirements-dev.txt
setup.cfg
setup.py
staty/__init__.py
staty/base.py
staty/codes.py
staty/exceptions.py
staty/status_map.py
staty/utils.py
staty.egg-info/PKG-INFO
staty.egg-info/SOURCES.txt
staty.egg-info/dependency_links.txt
staty.egg-info/requires.txt
staty.egg-info/top_level.txt