Metadata-Version: 2.1
Name: staty
Version: 1.2.3
Summary: HTTP response and status code handling
Home-page: http://github.com/osantana/staty
Author: Osvaldo Santana Neto
Author-email: staty@osantana.me
License: MIT
Download-URL: https://github.com/osantana/staty/tarball/1.2.3
Platform: any
Classifier: Development Status :: 5 - Production/Stable
Classifier: Intended Audience :: Developers
Classifier: License :: OSI Approved :: MIT License
Classifier: Natural Language :: English
Classifier: Operating System :: OS Independent
Classifier: Programming Language :: Python
Classifier: Programming Language :: Python :: 2
Classifier: Programming Language :: Python :: 2.7
Classifier: Programming Language :: Python :: 3
Classifier: Programming Language :: Python :: 3.5
Classifier: Programming Language :: Python :: Implementation :: PyPy
Classifier: Topic :: Software Development :: Libraries
Provides-Extra: requests
